setup.cfg
setup.py
quack/__init__.py
quack/quack.py
quack.egg-info/PKG-INFO
quack.egg-info/SOURCES.txt
quack.egg-info/dependency_links.txt
quack.egg-info/entry_points.txt
quack.egg-info/requires.txt
quack.egg-info/top_level.txt