Metadata-Version: 1.1
Name: quack
Version: 0.1
Summary: Insert specific module / folder from given repositories in yaml configurations.
Home-page: https://github.com/zonito/quack
Author: Love Sharma
Author-email: contact@lovesharma.com
License: MIT
Download-URL: https://github.com/zonito/quack/archive/0.1.tar.gz
Keywords: quack,build,submodule,module,dependencies
Platform: UNKNOWN
